securecrypto_bridge/SecureCrypto.dll
securecrypto_bridge/__init__.py
securecrypto_bridge/py.typed
securecrypto_bridge/securecrypto.py
securecrypto_bridge-1.0.1.dist-info/licenses/LICENSE
securecrypto_bridge-1.0.1.dist-info/METADATA
securecrypto_bridge-1.0.1.dist-info/WHEEL
securecrypto_bridge-1.0.1.dist-info/top_level.txt
securecrypto_bridge-1.0.1.dist-info/RECORD
