Metadata-Version: 2.4
Name: securecrypto-bridge
Version: 1.0.1
Summary: Python bridge for SecureCrypto.dll: encryption, hashing, signing, key management
Author-email: Jeremy <jeremiahstevens@gmial.com>
License-Expression: MIT
Project-URL: Homepage, https://github.com/nitestryker/SecureCrypto-PythonBridge
Project-URL: Issues, https://github.com/nitestryker/SecureCrypto-PythonBridge/issues
Project-URL: Source, https://github.com/nitestryker/SecureCrypto-PythonBridge
Classifier: Programming Language :: Python :: 3
Classifier: Operating System :: Microsoft :: Windows
Classifier: Topic :: Security :: Cryptography
Requires-Python: >=3.8
License-File: LICENSE
Dynamic: license-file
